{
  "index": {
    "horror": {
      "movies": 3,
      "series": 0
    },
    "thriller": {
      "movies": 9,
      "series": 0
    },
    "action": {
      "movies": 10,
      "series": 0
    },
    "science_fiction": {
      "movies": 4,
      "series": 0
    },
    "fantasy": {
      "movies": 1,
      "series": 0
    },
    "romance": {
      "movies": 2,
      "series": 0
    },
    "crime": {
      "movies": 4,
      "series": 0
    },
    "comedy": {
      "movies": 1,
      "series": 0
    },
    "mystery": {
      "movies": 1,
      "series": 0
    },
    "adventure": {
      "movies": 1,
      "series": 0
    },
    "action_&_adventure": {
      "movies": 0,
      "series": 1
    },
    "drama": {
      "movies": 0,
      "series": 1
    }
  },
  "docs": {
    "horror": {
      "genre": "Horror",
      "movies": [
        "Cp5yw52jE8LiILR4k8Q0",
        "2kVl2b7BH2N3MpF0rdLE",
        "0SIEDQmNm3ckD63cSn39"
      ],
      "series": []
    },
    "thriller": {
      "genre": "Thriller",
      "movies": [
        "Cp5yw52jE8LiILR4k8Q0",
        "2kVl2b7BH2N3MpF0rdLE",
        "wToY8NdFXOeyyWeHWfQX",
        "3zkQpB1Fr16VIqo8Z0xM",
        "OJeoH7AxlEhD77oqzNzG",
        "0jYGNU4tO2PltFh9O0vH",
        "80L9LrGKyODq1fk41wrE",
        "ZcQvhDa8PTaMoMVwS5Y2",
        "OmNdS4rfAZwFGLWErwby"
      ],
      "series": []
    },
    "action": {
      "genre": "Action",
      "movies": [
        "wToY8NdFXOeyyWeHWfQX",
        "3zkQpB1Fr16VIqo8Z0xM",
        "tYDisH9mryshVwGelBMH",
        "vA1fsJjK5N2z108dPo24",
        "iMC9sCby29flWILi2xR1",
        "JfN1fXvg3kDA2CpsJdyW",
        "0jYGNU4tO2PltFh9O0vH",
        "80L9LrGKyODq1fk41wrE",
        "ZcQvhDa8PTaMoMVwS5Y2",
        "OmNdS4rfAZwFGLWErwby"
      ],
      "series": []
    },
    "science_fiction": {
      "genre": "Science Fiction",
      "movies": [
        "wToY8NdFXOeyyWeHWfQX",
        "OJeoH7AxlEhD77oqzNzG",
        "iMC9sCby29flWILi2xR1",
        "JfN1fXvg3kDA2CpsJdyW"
      ],
      "series": []
    },
    "fantasy": {
      "genre": "Fantasy",
      "movies": [
        "0SIEDQmNm3ckD63cSn39"
      ],
      "series": []
    },
    "romance": {
      "genre": "Romance",
      "movies": [
        "0SIEDQmNm3ckD63cSn39",
        "OJeoH7AxlEhD77oqzNzG"
      ],
      "series": []
    },
    "crime": {
      "genre": "Crime",
      "movies": [
        "3zkQpB1Fr16VIqo8Z0xM",
        "tYDisH9mryshVwGelBMH",
        "0jYGNU4tO2PltFh9O0vH",
        "80L9LrGKyODq1fk41wrE"
      ],
      "series": []
    },
    "comedy": {
      "genre": "Comedy",
      "movies": [
        "tYDisH9mryshVwGelBMH"
      ],
      "series": []
    },
    "mystery": {
      "genre": "Mystery",
      "movies": [
        "vA1fsJjK5N2z108dPo24"
      ],
      "series": []
    },
    "adventure": {
      "genre": "Adventure",
      "movies": [
        "iMC9sCby29flWILi2xR1"
      ],
      "series": []
    },
    "action_&_adventure": {
      "genre": "Action & Adventure",
      "movies": [],
      "series": [
        "YPZrYRbJngKvIYD6NSg2"
      ]
    },
    "drama": {
      "genre": "Drama",
      "movies": [],
      "series": [
        "YPZrYRbJngKvIYD6NSg2"
      ]
    }
  },
  "exported_at": "2025-12-15T11:18:24.435Z"
}